morph_ko.py
morph_ko-0.1.0.dist-info/WHEEL
morph_ko-0.1.0.dist-info/METADATA
morph_ko-0.1.0.dist-info/RECORD
