Metadata-Version: 2.1
Name: morph-ko
Version: 0.1.0
Summary: Utility for generating variations of Korean words
Home-page: https://github.com/MatMoore/morph
License: MIT
Author: Mat Moore
Author-email: matmoore@users.noreply.github.com
Requires-Python: >=3.10,<4.0
Classifier: License :: OSI Approved :: MIT License
Classifier: Programming Language :: Python :: 3
Classifier: Programming Language :: Python :: 3.10
Project-URL: Repository, https://github.com/MatMoore/morph
